parallelworkloads/__init__.py
parallelworkloads/lublin99.cpython-38-darwin.so
parallelworkloads/swf.cpython-38-darwin.so
parallelworkloads/tsafrir05.cpython-38-darwin.so
parallelworkloads-0.1.3.dist-info/METADATA
parallelworkloads-0.1.3.dist-info/WHEEL
parallelworkloads-0.1.3.dist-info/top_level.txt
parallelworkloads-0.1.3.dist-info/RECORD
