Metadata-Version: 2.1
Name: parallelworkloads
Version: 0.1.3
Summary: A Python Wrapper for the workload model proposed by Lublin
Home-page: https://github.com/renatolfc/parallelworkloads
Author: Renato L. de F. Cunha
Author-email: renatocunha@acm.org
License: UNKNOWN
Project-URL: Bug Reports, https://github.com/renatolfc/parallelworkloads/issues
Project-URL: Say Thanks!, https://saythanks.io/to/renatocunha%40acm.org
Project-URL: Source, https://github.com/renatolfc/parallelworkloads
Keywords: workload,standard workload format,swf
Platform: UNKNOWN
Classifier: Development Status :: 3 - Alpha
Classifier: Intended Audience :: Developers
Classifier: Intended Audience :: Information Technology
Classifier: Topic :: Scientific/Engineering
Classifier: Topic :: Scientific/Engineering :: Artificial Intelligence
Classifier: License :: OSI Approved :: MIT License
Classifier: Programming Language :: Python :: 3
Classifier: Programming Language :: Python :: 3.6
Classifier: Programming Language :: Python :: 3.7
Classifier: Programming Language :: Python :: 3.8
Classifier: Programming Language :: Python :: 3.9
Classifier: Programming Language :: Python :: 3.10
Classifier: Programming Language :: Python :: 3 :: Only
Requires-Python: >=3.6, <4
Provides-Extra: dev
